structocr/__init__.py
structocr/client.py
structocr-1.1.3.dist-info/METADATA
structocr-1.1.3.dist-info/WHEEL
structocr-1.1.3.dist-info/top_level.txt
structocr-1.1.3.dist-info/RECORD
