Metadata-Version: 2.1
Name: structocr
Version: 1.1.3
Summary: The official Python SDK for StructOCR API - Passport, ID card, Driver License OCR, and Invoice.
Home-page: https://structocr.com
Author: StructOCR Team
Author-email: support@structocr.com
Project-URL: Homepage, https://structocr.com
Project-URL: Documentation, https://www.structocr.com/developers
Project-URL: Source, https://github.com/structocr/structocr-python
Project-URL: Tracker, https://github.com/structocr/structocr-python/issues
Classifier: Programming Language :: Python :: 3
Classifier: License :: OSI Approved :: MIT License
Classifier: Operating System :: OS Independent
Classifier: Topic :: Scientific/Engineering :: Image Recognition
Requires-Python: >=3.6
Requires-Dist: requests (>=2.25.0)
